collapsing_thread_pool_executor/__init__.py
collapsing_thread_pool_executor/collapsing_thread_pool_executor.py
collapsing_thread_pool_executor/collapsing_thread_pool_executor_test.py
collapsing_thread_pool_executor-2020.7.18.data/data/README.md
collapsing_thread_pool_executor-2020.7.18.dist-info/LICENSE
collapsing_thread_pool_executor-2020.7.18.dist-info/METADATA
collapsing_thread_pool_executor-2020.7.18.dist-info/WHEEL
collapsing_thread_pool_executor-2020.7.18.dist-info/top_level.txt
collapsing_thread_pool_executor-2020.7.18.dist-info/RECORD
