Metadata-Version: 2.1
Name: collapsing-thread-pool-executor
Version: 2020.7.18
Summary: A thread pool that auto-manages the number of worker threads and is compatible with the "futures" module ThreadPoolExecutor interface.
Home-page: https://github.com/initialed85/collapsing-thread-pool-executor
Author: Edward Beech
Author-email: initialed85@gmail.com
License: MIT
Keywords: sample setuptools development
Platform: UNKNOWN
Classifier: Development Status :: 3 - Alpha
Classifier: Intended Audience :: Developers
Classifier: Topic :: Software Development :: Libraries
Classifier: License :: OSI Approved :: MIT License
Classifier: Programming Language :: Python :: 2.7
Classifier: Programming Language :: Python :: 3.6
Requires-Dist: futures (<4.0.0,>=3.2.0)
Provides-Extra: dev
Requires-Dist: check-manifest ; extra == 'dev'
Provides-Extra: test
Requires-Dist: coverage ; extra == 'test'
